{
  "packageId": "io.github.u477studio.twa",
  "host": "u477studio.github.io",
  "name": "Emabol Champ",
  "launcherName": "Emabol",
  "display": "fullscreen",
  "themeColor": "#05050F",
  "themeColorDark": "#000000",
  "navigationColor": "#000000",
  "navigationColorDark": "#000000",
  "navigationDividerColor": "#000000",
  "navigationDividerColorDark": "#000000",
  "backgroundColor": "#05050F",
  "enableNotifications": true,
  "startUrl": "/Emabol-Champ",
  "iconUrl": "https://u477studio.github.io/Emabol-Champ/icons/icon-512x512.png",
  "maskableIconUrl": "https://u477studio.github.io/Emabol-Champ/icons/icon-512x512.png",
  "splashScreenFadeOutDuration": 300,
  "signingKey": {
    "path": "D:\\emabol-champ\\emabol-twa\\android.keystore",
    "alias": "android"
  },
  "appVersionName": "1",
  "appVersionCode": 1,
  "shortcuts": [],
  "generatorApp": "bubblewrap-cli",
  "webManifestUrl": "https://u477studio.github.io/Emabol-Champ/manifest.json",
  "fallbackType": "customtabs",
  "features": {},
  "alphaDependencies": {
    "enabled": false
  },
  "enableSiteSettingsShortcut": true,
  "isChromeOSOnly": false,
  "isMetaQuest": false,
  "fullScopeUrl": "https://u477studio.github.io/Emabol-Champ/",
  "minSdkVersion": 21,
  "orientation": "portrait",
  "fingerprints": [],
  "additionalTrustedOrigins": [],
  "retainedBundles": [],
  "protocolHandlers": [],
  "fileHandlers": [],
  "launchHandlerClientMode": "",
  "displayOverride": [],
  "appVersion": "1"
}